mini_pole/__init__.py
mini_pole/con_map.py
mini_pole/esprit.py
mini_pole/green_func.py
mini_pole/mini_pole.py
mini_pole/mini_pole_dlr.py
mini_pole/mini_pole_rf.py
mini_pole/mini_pole_rf_dpr.py
mini_pole/spectrum_example.py
mini_pole-0.5.dist-info/licenses/LICENSE
mini_pole-0.5.dist-info/METADATA
mini_pole-0.5.dist-info/WHEEL
mini_pole-0.5.dist-info/top_level.txt
mini_pole-0.5.dist-info/RECORD
