Metadata-Version: 2.4
Name: mini_pole
Version: 0.5
Summary: This Python code implements the Minimal Pole Method (MPM) for both Matsubara and real-frequency data.
Home-page: https://github.com/Green-Phys/MiniPole
Author: Lei Zhang
Author-email: lzphy@umich.edu
License: MIT
Classifier: Programming Language :: Python :: 3
Classifier: License :: OSI Approved :: MIT License
Classifier: Operating System :: OS Independent
Requires-Python: >=3.8
License-File: LICENSE
Requires-Dist: numpy>=1.21.0
Requires-Dist: scipy>=1.7.0
Dynamic: author
Dynamic: author-email
Dynamic: classifier
Dynamic: description
Dynamic: description-content-type
Dynamic: home-page
Dynamic: license
Dynamic: license-file
Dynamic: requires-dist
Dynamic: requires-python
Dynamic: summary
